{"interfaceLanguages":{"swift":[{"children":[{"title":"Extended Modules","type":"groupMarker"},{"children":[{"title":"Extended Structures","type":"groupMarker"},{"children":[{"title":"Instance Methods","type":"groupMarker"},{"path":"\/documentation\/nestedtypes\/somesymbolkitextension\/externaltype\/foo()","title":"func foo()","type":"method"}],"path":"\/documentation\/nestedtypes\/somesymbolkitextension\/externaltype","title":"SymbolGraph.ExternalType","type":"extension"}],"path":"\/documentation\/nestedtypes\/somesymbolkitextension","title":"SomeSymbolKitExtension","type":"extension"},{"children":[{"title":"Extended Classes","type":"groupMarker"},{"children":[{"title":"Instance Methods","type":"groupMarker"},{"path":"\/documentation\/nestedtypes\/symbolkit\/symbol-swift.class.extension\/foo()","title":"func foo()","type":"method"}],"path":"\/documentation\/nestedtypes\/symbolkit\/symbol-swift.class.extension","title":"UnifiedSymbolGraph.Symbol","type":"extension"},{"title":"Extended Structures","type":"groupMarker"},{"children":[{"title":"Instance Methods","type":"groupMarker"},{"path":"\/documentation\/nestedtypes\/symbolkit\/symbol-swift.struct.extension\/foo()","title":"func foo()","type":"method"}],"path":"\/documentation\/nestedtypes\/symbolkit\/symbol-swift.struct.extension","title":"SymbolGraph.Symbol","type":"extension"},{"title":"Extended Enumerations","type":"groupMarker"},{"children":[{"title":"Instance Methods","type":"groupMarker"},{"path":"\/documentation\/nestedtypes\/symbolkit\/kind\/foo()","title":"func foo()","type":"method"}],"path":"\/documentation\/nestedtypes\/symbolkit\/kind","title":"SymbolGraph.Symbol.Swift.GenericConstraint.Kind","type":"extension"}],"path":"\/documentation\/nestedtypes\/symbolkit","title":"SymbolKit","type":"extension"}],"path":"\/documentation\/nestedtypes","title":"NestedTypes","type":"module"}]},"schemaVersion":{"major":0,"minor":1,"patch":0}}